ward/__init__.py
ward/ward.py
ward_lang-0.0.11.dist-info/METADATA
ward_lang-0.0.11.dist-info/WHEEL
ward_lang-0.0.11.dist-info/top_level.txt
ward_lang-0.0.11.dist-info/RECORD
